{
  "Websites": [
    {
      "id": 1,
      "name": "avenueatyork.com"
    },
    {
      "id": 2,
      "name": "https://www.livethekendrick.com/"
    }
  ],

  "sources-avenueatyork": [
    {
      "id": "pws",
      "tag": "pws",
      "source": "PropertyWebsite",
      "Shown_form": "Prospect & Agent"
    },
    {
      "id": "rwg",
      "tag": "rwg",
      "source": "RentalsGoneWild.com",
      "Shown_form": "Prospect & Agent"
    },
    {
      "id": "apt",
      "tag": "apt",
      "source": "apartments.com",
      "Shown_form": "Prospect & Agent"
    }
  ],

  "medium-avenueatyork": [
    {
      "id": "e",
      "Medium": "Email"
    },
    {
      "id": "p",
      "Medium": "Phone"
    },
    {
      "id": "wi",
      "Medium": "Walk-In"
    }
  ],

  "content-avenueatyork": [],
  "channel-avenueatyork": [
    {
      "id": "ag",
      "Channel": "Agent"
    },
    {
      "id": "api",
      "Channel": "API"
    },
    {
      "id": "cc",
      "Channel": "Callcenter"
    }
  ],

  "DNI-avenueatyork": {
    "tel": "111-111-111"
  }
}
